{
  "channel_id": "UCHVgNZeav4snXQs93TyNp8g",
  "channel_name": "熊本県民テレビ KKT公式チャンネル",
  "updated_at": "2025-03-07T23:18:07.581203",
  "videos": [
    {
      "id": "7KsQaVpnoDA",
      "title": "【ウクライナ侵攻3年】父は日本人、母はウクライナ人　熊本へやってきた中学生が卒業",
      "thumbnail": "https://i.ytimg.com/vi/7KsQaVpnoDA/maxresdefault.jpg",
      "url": "https://www.youtube.com/watch?v=7KsQaVpnoDA"
    },
    {
      "id": "RopRebAiWGY",
      "title": "【一発では読めない?】｢五霊中学校｣近くに｢五両バス停｣… 熊本市 難読地名のナゾ",
      "thumbnail": "https://i.ytimg.com/vi/RopRebAiWGY/maxresdefault.jpg",
      "url": "https://www.youtube.com/watch?v=RopRebAiWGY"
    },
    {
      "id": "GrOblNoeNBc",
      "title": "【くまモン15周年】ミニ四駆や高良健吾さん製作のTシャツも! コラボグッズがお披露目",
      "thumbnail": "https://i.ytimg.com/vi/GrOblNoeNBc/maxresdefault.jpg",
      "url": "https://www.youtube.com/watch?v=GrOblNoeNBc"
    },
    {
      "id": "HwzPQvEomsA",
      "title": "【懲戒免職】甲佐町職員｢パチンコなどで借金かさみ…｣ 互助会費15万円盗む",
      "thumbnail": "https://i.ytimg.com/vi/HwzPQvEomsA/maxresdefault.jpg",
      "url": "https://www.youtube.com/watch?v=HwzPQvEomsA"
    },
    {
      "id": "nlvPiOtgoMc",
      "title": "居酒屋全焼の火事 焼け跡から発見の遺体は経営者の男性と発表 上天草市",
      "thumbnail": "https://i.ytimg.com/vi/nlvPiOtgoMc/maxresdefault.jpg",
      "url": "https://www.youtube.com/watch?v=nlvPiOtgoMc"
    },
    {
      "id": "ufATMylaW98",
      "title": "【道路陥没】老朽化した下水管取り換え工事 接続部分に約2センチの隙間が見つかる",
      "thumbnail": "https://i.ytimg.com/vi/ufATMylaW98/maxresdefault.jpg",
      "url": "https://www.youtube.com/watch?v=ufATMylaW98"
    },
    {
      "id": "iO2DqGd3iHg",
      "title": "【コンビニ強盗】車で突っ込み白い仮面をつけタバコ2箱を奪う 強盗の疑いで45歳の男を逮捕",
      "thumbnail": "https://i.ytimg.com/vi/iO2DqGd3iHg/maxresdefault.jpg",
      "url": "https://www.youtube.com/watch?v=iO2DqGd3iHg"
    },
    {
      "id": "91Pz_33GmYc",
      "title": "【日産】ホンハイが買収するのか？台湾ジャーナリストが鴻海の内部事情を語ります",
      "thumbnail": "https://i.ytimg.com/vi/91Pz_33GmYc/maxresdefault.jpg",
      "url": "https://www.youtube.com/watch?v=91Pz_33GmYc"
    },
    {
      "id": "li8Y3pCz9uA",
      "title": "【深夜のコンビニ】仮面をつけ刃物を持ってタバコ2箱を奪い逃走 強盗の疑いで45歳の男を逮捕｜大津町",
      "thumbnail": "https://i.ytimg.com/vi/li8Y3pCz9uA/maxresdefault.jpg",
      "url": "https://www.youtube.com/watch?v=li8Y3pCz9uA"
    },
    {
      "id": "-7axvDZBTIg",
      "title": "新1年生を交通事故から守ろう 熊本県トラック協会が交通ルール書かれたファイルを贈呈",
      "thumbnail": "https://i.ytimg.com/vi/-7axvDZBTIg/maxresdefault.jpg",
      "url": "https://www.youtube.com/watch?v=-7axvDZBTIg"
    },
    {
      "id": "jiT6KsjT1dE",
      "title": "合志市に新たな認可保育園開設 4月から80人受け入れ予定→すでに70人以上予約",
      "thumbnail": "https://i.ytimg.com/vi/jiT6KsjT1dE/maxresdefault.jpg",
      "url": "https://www.youtube.com/watch?v=jiT6KsjT1dE"
    },
    {
      "id": "R1KMeWX3xeU",
      "title": "90代女性の銀行口座から約416万円引き出し盗んだ疑いの男逮捕 ｢承諾を受けた｣と否認",
      "thumbnail": "https://i.ytimg.com/vi/R1KMeWX3xeU/maxresdefault.jpg",
      "url": "https://www.youtube.com/watch?v=R1KMeWX3xeU"
    },
    {
      "id": "cHYHrKjHhhk",
      "title": "【半導体】増加が見込まれる企業の排水 新たな下水処理施設整備の都市計画案が了承",
      "thumbnail": "https://i.ytimg.com/vi/cHYHrKjHhhk/maxresdefault.jpg",
      "url": "https://www.youtube.com/watch?v=cHYHrKjHhhk"
    },
    {
      "id": "Xyp5wxmN_hU",
      "title": "【阿蘇】松嶋和子市長が初登庁｢一緒に新しい阿蘇市を｣熊本の市町村で初の女性首長",
      "thumbnail": "https://i.ytimg.com/vi/Xyp5wxmN_hU/maxresdefault.jpg",
      "url": "https://www.youtube.com/watch?v=Xyp5wxmN_hU"
    },
    {
      "id": "L_N6Vjmz6Pw",
      "title": "「アクセルとブレーキを踏み間違えた」軽自動車が店舗に突っ込む事故 人吉市",
      "thumbnail": "https://i.ytimg.com/vi/L_N6Vjmz6Pw/maxresdefault.jpg",
      "url": "https://www.youtube.com/watch?v=L_N6Vjmz6Pw"
    },
    {
      "id": "B1mJ6S69CPY",
      "title": "TSMCが進出した菊陽町に｢日台会館｣がオープン 結婚式場や日本と台湾の交流の場にも",
      "thumbnail": "https://i.ytimg.com/vi/B1mJ6S69CPY/maxresdefault.jpg",
      "url": "https://www.youtube.com/watch?v=B1mJ6S69CPY"
    },
    {
      "id": "x29H-hrl7y8",
      "title": "【地震で液状化】2025年度末にも対策事業完了の見通し 熊本市南区の工事終わり経過観察",
      "thumbnail": "https://i.ytimg.com/vi/x29H-hrl7y8/maxresdefault.jpg",
      "url": "https://www.youtube.com/watch?v=x29H-hrl7y8"
    },
    {
      "id": "ylm_8xMTkLc",
      "title": "【半導体】熊本版サイエンスパークは\"分散型\" セミコンテクノパーク中心に複数の拠点 3月中に基本方針を公表",
      "thumbnail": "https://i.ytimg.com/vi/ylm_8xMTkLc/maxresdefault.jpg",
      "url": "https://www.youtube.com/watch?v=ylm_8xMTkLc"
    },
    {
      "id": "w0uxp5fXXFU",
      "title": "【大江戸展】老舗店の天丼やクリーム大福などスイーツ･伝統工芸などが鶴屋百貨店に集結!",
      "thumbnail": "https://i.ytimg.com/vi/w0uxp5fXXFU/maxresdefault.jpg",
      "url": "https://www.youtube.com/watch?v=w0uxp5fXXFU"
    },
    {
      "id": "dZt__BXFC3U",
      "title": "｢指示通り動くだけで40万円｣SNSで闇バイト募集した罪に問われた男の初公判 男は無罪を主張",
      "thumbnail": "https://i.ytimg.com/vi/dZt__BXFC3U/maxresdefault.jpg",
      "url": "https://www.youtube.com/watch?v=dZt__BXFC3U"
    },
    {
      "id": "hncVGkiVlAg",
      "title": "水俣市の飲食店でノロウイルスによる食中毒 15人が症状訴え 2日間の営業停止処分",
      "thumbnail": "https://i.ytimg.com/vi/hncVGkiVlAg/maxresdefault.jpg",
      "url": "https://www.youtube.com/watch?v=hncVGkiVlAg"
    },
    {
      "id": "jMvJD5KscS0",
      "title": "【熊本市電】4月5日から一部増便へ ラッシュ時に合わせて新水前寺駅前からの始発便も追加",
      "thumbnail": "https://i.ytimg.com/vi/jMvJD5KscS0/maxresdefault.jpg",
      "url": "https://www.youtube.com/watch?v=jMvJD5KscS0"
    },
    {
      "id": "DlwV6yYvpSc",
      "title": "【熊本市】新副市長に田中俊実上下水道事業管理者の方針示す 3月で任期満了の深水副市長の後任",
      "thumbnail": "https://i.ytimg.com/vi/DlwV6yYvpSc/maxresdefault.jpg",
      "url": "https://www.youtube.com/watch?v=DlwV6yYvpSc"
    },
    {
      "id": "YxrwJdG8W08",
      "title": "「廃業の増加が続く見込み」去年休廃業・解散した熊本県内企業は前年から大幅増 増加率は秋田県に次ぎ全国2位",
      "thumbnail": "https://i.ytimg.com/vi/YxrwJdG8W08/maxresdefault.jpg",
      "url": "https://www.youtube.com/watch?v=YxrwJdG8W08"
    },
    {
      "id": "ReDliHj5_jQ",
      "title": "【命の大切さを学ぶ】｢ゆりかご｣に預け入れられた宮津航一さんが設立 3回目の｢子ども大学くまもと｣",
      "thumbnail": "https://i.ytimg.com/vi/ReDliHj5_jQ/maxresdefault.jpg",
      "url": "https://www.youtube.com/watch?v=ReDliHj5_jQ"
    },
    {
      "id": "bjf3uzFxoYM",
      "title": "【解説】草原に火を放つ阿蘇の｢野焼き｣はなぜ必要？植物にダメージは？県民のギモン",
      "thumbnail": "https://i.ytimg.com/vi/bjf3uzFxoYM/maxresdefault.jpg",
      "url": "https://www.youtube.com/watch?v=bjf3uzFxoYM"
    },
    {
      "id": "I4cqq7LaCyo",
      "title": "【日本一】再春館製薬所バドミントン部が優勝報告 2年ぶりにTOP4トーナメント制す",
      "thumbnail": "https://i.ytimg.com/vi/I4cqq7LaCyo/maxresdefault.jpg",
      "url": "https://www.youtube.com/watch?v=I4cqq7LaCyo"
    },
    {
      "id": "d3E6CmKojE8",
      "title": "【売り手市場の就活】学生の重視ポイントは『安定』熊本県内最大級の合同会社説明会",
      "thumbnail": "https://i.ytimg.com/vi/d3E6CmKojE8/maxresdefault.jpg",
      "url": "https://www.youtube.com/watch?v=d3E6CmKojE8"
    },
    {
      "id": "TtZYwxFpxME",
      "title": "【修学旅行で見学も】大阪･関西万博を身近に感じて 八代市の中学校で特別授業",
      "thumbnail": "https://i.ytimg.com/vi/TtZYwxFpxME/maxresdefault.jpg",
      "url": "https://www.youtube.com/watch?v=TtZYwxFpxME"
    },
    {
      "id": "s-Azy3B_U_w",
      "title": "動画撮影しながら消防に通報できる｢Live119｣とAEDマップを連携へ 熊本市消防局",
      "thumbnail": "https://i.ytimg.com/vi/s-Azy3B_U_w/maxresdefault.jpg",
      "url": "https://www.youtube.com/watch?v=s-Azy3B_U_w"
    },
    {
      "id": "W27pc_ZaS0o",
      "title": "【九州の備蓄拠点】益城町が選ばれた理由とは？災害時に支援物資を届ける倉庫を公開",
      "thumbnail": "https://i.ytimg.com/vi/W27pc_ZaS0o/maxresdefault.jpg",
      "url": "https://www.youtube.com/watch?v=W27pc_ZaS0o"
    },
    {
      "id": "dYO78eG7tcQ",
      "title": "【ひなまつり】町一体で行われるひなまつりイベント 幕末時代のひな人形も！？｜人吉・球磨",
      "thumbnail": "https://i.ytimg.com/vi/dYO78eG7tcQ/maxresdefault.jpg",
      "url": "https://www.youtube.com/watch?v=dYO78eG7tcQ"
    },
    {
      "id": "p3ImcevSSEY",
      "title": "【事故】道路を横断していた67歳の男性が車にはねられ意識不明の重体 熊本市",
      "thumbnail": "https://i.ytimg.com/vi/p3ImcevSSEY/maxresdefault.jpg",
      "url": "https://www.youtube.com/watch?v=p3ImcevSSEY"
    },
    {
      "id": "a-6jU4za6dM",
      "title": "戌の日｜産婦人科として伝えたいこと",
      "thumbnail": "https://i.ytimg.com/vi/a-6jU4za6dM/maxresdefault.jpg",
      "url": "https://www.youtube.com/watch?v=a-6jU4za6dM"
    },
    {
      "id": "QIr2c8pnGkM",
      "title": "無罪訴えながら死刑執行\"菊池事件\" 法医学者が新たに｢凶器｣の矛盾を指摘",
      "thumbnail": "https://i.ytimg.com/vi/QIr2c8pnGkM/maxresdefault.jpg",
      "url": "https://www.youtube.com/watch?v=QIr2c8pnGkM"
    },
    {
      "id": "zyLYfDmzCaw",
      "title": "【門外不出の栽培技術】不規則な曲がりの茎が特徴的な\"くまもと踊る丹頂\"が全国から注目！",
      "thumbnail": "https://i.ytimg.com/vi/zyLYfDmzCaw/maxresdefault.jpg",
      "url": "https://www.youtube.com/watch?v=zyLYfDmzCaw"
    },
    {
      "id": "Rs7SAYrt_T8",
      "title": "生まれてくるあなたへ｢0回目のひなまつり｣ お腹の赤ちゃんへ健やかな成長願う",
      "thumbnail": "https://i.ytimg.com/vi/Rs7SAYrt_T8/maxresdefault.jpg",
      "url": "https://www.youtube.com/watch?v=Rs7SAYrt_T8"
    },
    {
      "id": "ORg-bxfVsw0",
      "title": "【IMAT】凶悪事件発生時に医療チームが現場へ 熊本県警が4医療機関とIMAT派遣協定",
      "thumbnail": "https://i.ytimg.com/vi/ORg-bxfVsw0/maxresdefault.jpg",
      "url": "https://www.youtube.com/watch?v=ORg-bxfVsw0"
    },
    {
      "id": "MT_7IsNQxxU",
      "title": "3歳の娘が殺されネットの誹謗中傷に｢死のうと思った…｣ あれから14年 両親の胸の内は",
      "thumbnail": "https://i.ytimg.com/vi/MT_7IsNQxxU/maxresdefault.jpg",
      "url": "https://www.youtube.com/watch?v=MT_7IsNQxxU"
    },
    {
      "id": "Jcn_Ln18d7c",
      "title": "【3月2日】ワンピースのサンジの誕生日を益城町の像前でお祝い",
      "thumbnail": "https://i.ytimg.com/vi/Jcn_Ln18d7c/maxresdefault.jpg",
      "url": "https://www.youtube.com/watch?v=Jcn_Ln18d7c"
    },
    {
      "id": "DfRxoRHa8tw",
      "title": "【TSMC開所から1年】工場進出の陰で泣いている農家もいる… 熊本の未来は？｜半導体×農業",
      "thumbnail": "https://i.ytimg.com/vi/DfRxoRHa8tw/maxresdefault.jpg",
      "url": "https://www.youtube.com/watch?v=DfRxoRHa8tw"
    },
    {
      "id": "qJGynGlocS0",
      "title": "【初午大祭】熊本城稻荷神社熱鬧非凡 參拜者祈求福運 撒餅活動還有「中獎福餅」！｜KKT NEWS @KKTNEWS.TAIWAN",
      "thumbnail": "https://i.ytimg.com/vi/qJGynGlocS0/maxresdefault.jpg",
      "url": "https://www.youtube.com/watch?v=qJGynGlocS0"
    },
    {
      "id": "ZLtZP-OxXE0",
      "title": "【書道】本格的に書道を始めたばかりのキャリア１年目で全国書道展で第２席となる外務大臣賞を受賞！｜御船高校書道部 大野愛莉さん",
      "thumbnail": "https://i.ytimg.com/vi/ZLtZP-OxXE0/maxresdefault.jpg",
      "url": "https://www.youtube.com/watch?v=ZLtZP-OxXE0"
    },
    {
      "id": "ogUUvDrTcGs",
      "title": "【注意】長時間使用手機恐損害視力… 「手機內斜視」嚴重時恐需多年治療！｜KKT NEWS @KKTNEWS.TAIWAN",
      "thumbnail": "https://i.ytimg.com/vi/ogUUvDrTcGs/maxresdefault.jpg",
      "url": "https://www.youtube.com/watch?v=ogUUvDrTcGs"
    },
    {
      "id": "Guld6gkgN8E",
      "title": "【轉讓的土地】熊本縣決定轉讓閒置 30 多年的縣有土地，泡沫經濟時期以 2 億 3800 萬日圓購入 → 1250 萬日圓轉讓｜高森町",
      "thumbnail": "https://i.ytimg.com/vi/Guld6gkgN8E/maxresdefault.jpg",
      "url": "https://www.youtube.com/watch?v=Guld6gkgN8E"
    },
    {
      "id": "lAoCH_P-JFs",
      "title": "銀行頭取も被害に… SNSを乗っ取られないためには? もし乗っ取られたら何をする?",
      "thumbnail": "https://i.ytimg.com/vi/lAoCH_P-JFs/maxresdefault.jpg",
      "url": "https://www.youtube.com/watch?v=lAoCH_P-JFs"
    },
    {
      "id": "dWEAOMARRGU",
      "title": "「最高の出来」スイカの生産量日本一の熊本で出荷始まる 全国に約142万玉出荷の見込み",
      "thumbnail": "https://i.ytimg.com/vi/dWEAOMARRGU/maxresdefault.jpg",
      "url": "https://www.youtube.com/watch?v=dWEAOMARRGU"
    },
    {
      "id": "wf8OGEEjBfM",
      "title": "「出来心で…」パチンコ店駐車場で拾った1万5千円相当が入ったICカードを換金した自衛官停職処分",
      "thumbnail": "https://i.ytimg.com/vi/wf8OGEEjBfM/maxresdefault.jpg",
      "url": "https://www.youtube.com/watch?v=wf8OGEEjBfM"
    },
    {
      "id": "bG7qCCg5S6I",
      "title": "【ダイエーから44年】イオン熊本中央店が閉店 たくさんの思い出と迎えた最後の営業日",
      "thumbnail": "https://i.ytimg.com/vi/bG7qCCg5S6I/maxresdefault.jpg",
      "url": "https://www.youtube.com/watch?v=bG7qCCg5S6I"
    },
    {
      "id": "eJtMR0QslKQ",
      "title": "【熊本県議会】総額563億円の一般会計補正予算案を可決 福祉などに従事する職員の処遇改善など",
      "thumbnail": "https://i.ytimg.com/vi/eJtMR0QslKQ/maxresdefault.jpg",
      "url": "https://www.youtube.com/watch?v=eJtMR0QslKQ"
    }
  ]
}